vite_fusion/__init__.py
vite_fusion-0.0.6.dist-info/LICENSE
vite_fusion-0.0.6.dist-info/METADATA
vite_fusion-0.0.6.dist-info/WHEEL
vite_fusion-0.0.6.dist-info/top_level.txt
vite_fusion-0.0.6.dist-info/RECORD
